nsdev/__init__.py
tesdikin-0.1.dist-info/METADATA
tesdikin-0.1.dist-info/WHEEL
tesdikin-0.1.dist-info/top_level.txt
tesdikin-0.1.dist-info/RECORD
